Metadata-Version: 1.0
Name: superzajebistapaczkaktorarozwalicimozg
Version: 0.1.0
Summary: Pokochasz tą paczke od pierwszych chwil
Home-page: UNKNOWN
Author: Frank Sinatra
Author-email: lew_11@wp.pl
License: UNKNOWN
Platform: UNKNOWN
